{
  "annotations": {
    "list": [
      {
        "builtIn": 1,
        "datasource": {
          "type": "grafana",
          "uid": "-- Grafana --"
        },
        "enable": true,
        "hide": true,
        "iconColor": "rgba(0, 211, 255, 1)",
        "name": "Annotations & Alerts",
        "type": "dashboard"
      }
    ]
  },
  "editable": true,
  "fiscalYearStartMonth": 0,
  "graphTooltip": 0,
  "id": 26,
  "links": [],
  "panels": [
    {
      "datasource": {
        "type": "grafana-clickhouse-datasource",
        "uid": "denqrtvj4xvy8e"
      },
      "fieldConfig": {
        "defaults": {
          "mappings": [],
          "thresholds": {
            "mode": "percentage",
            "steps": [
              {
                "color": "green"
              },
              {
                "color": "orange",
                "value": 70
              },
              {
                "color": "red",
                "value": 85
              }
            ]
          }
        },
        "overrides": []
      },
      "gridPos": {
        "h": 8,
        "w": 12,
        "x": 0,
        "y": 0
      },
      "id": 1,
      "options": {
        "minVizHeight": 75,
        "minVizWidth": 75,
        "orientation": "auto",
        "reduceOptions": {
          "calcs": [
            "lastNotNull"
          ],
          "fields": "",
          "values": false
        },
        "showThresholdLabels": false,
        "showThresholdMarkers": false,
        "sizing": "auto"
      },
      "pluginVersion": "12.0.1",
      "targets": [
        {
          "datasource": {
            "type": "grafana-clickhouse-datasource",
            "uid": "denqrtvj4xvy8e"
          },
          "editorType": "sql",
          "format": 1,
          "meta": {
            "builderOptions": {
              "columns": [],
              "database": "",
              "limit": 1000,
              "mode": "list",
              "queryType": "table",
              "table": ""
            }
          },
          "pluginVersion": "4.9.0",
          "queryType": "table",
          "rawSql": "SELECT \r\n    total_revenue / total_sales_count AS average_check\r\nFROM average_sale_check;",
          "refId": "A"
        }
      ],
      "title": "average_sale_check",
      "type": "gauge"
    }
  ],
  "preload": false,
  "schemaVersion": 41,
  "tags": [],
  "templating": {
    "list": []
  },
  "time": {
    "from": "now-6h",
    "to": "now"
  },
  "timepicker": {},
  "timezone": "browser",
  "title": "average_sale_check",
  "uid": "04e2b65f-c1d9-4d2c-b975-ae720f6cabfe",
  "version": 1
}